semi_colon/__init__.py
semi_colon/bbox.py
semi_colon/colab.py
semi_colon/house.py
semi_colon/img2data.py
semi_colon/main.py
semi_colon/resources/boston_house_prices.csv
semi_colon/resources/descr.rst
semi_colon-0.2.12.dist-info/METADATA
semi_colon-0.2.12.dist-info/WHEEL
semi_colon-0.2.12.dist-info/top_level.txt
semi_colon-0.2.12.dist-info/RECORD
