Metadata-Version: 2.4
Name: semi-colon
Version: 0.2.12
Summary: semi-colon is a utility package for CV, data science, Machine Learning and Deep Learning.
Author-email: Lee Sewoo <dltpdn@gmail.com>
Project-URL: Homepage, http://semi-colon.kr
Project-URL: Repository, https://github.com/dltpdn/semi-colon
